repo_map/cache_manager.py
repo_map/cli_handler.py
repo_map/code_parser.py
repo_map/config.py
repo_map/file_scanner.py
repo_map/llm_service.py
repo_map/logging_utils.py
repo_map/main.py
repo_map/models.py
repo_map/py.typed
repo_map/report_generator.py
repo_map-0.6.0.dist-info/LICENSE
repo_map-0.6.0.dist-info/METADATA
repo_map-0.6.0.dist-info/WHEEL
repo_map-0.6.0.dist-info/entry_points.txt
repo_map-0.6.0.dist-info/RECORD
