Metadata-Version: 2.1
Name: repo-map
Version: 0.6.0
Summary: Generate a comprehensive summary and visualization of a repository structure, enhanced with AI-powered descriptions and developer considerations.
License: Apache-2.0
Author: Cyanheads
Author-email: casey@caseyjhand.com
Requires-Python: >=3.12,<4.0
Classifier: License :: OSI Approved :: Apache Software License
Classifier: Programming Language :: Python :: 3
Classifier: Programming Language :: Python :: 3.12
Classifier: Programming Language :: Python :: 3.13
Requires-Dist: aiohttp (>=3.9.5,<4.0.0)
Requires-Dist: certifi (>=2024.6.2,<2025.0.0)
Requires-Dist: pathspec (>=0.12.1,<0.13.0)
Requires-Dist: pydantic (>=2.7.4,<3.0.0)
Requires-Dist: pydantic-settings (>=2.3.4,<3.0.0)
Requires-Dist: tqdm (>=4.66.4,<5.0.0)
Requires-Dist: tree-sitter (>=0.21.3,<0.22.0)
Requires-Dist: tree-sitter-languages (>=1.10.2,<2.0.0)
Requires-Dist: types-tqdm (>=4.67.0.20250809,<5.0.0.0)
Project-URL: Homepage, https://github.com/cyanheads/repo-map
